pagarme_surfmappers/__init__.py
pagarme_surfmappers/bank.py
pagarme_surfmappers/bulk_anticipation.py
pagarme_surfmappers/constants.py
pagarme_surfmappers/exceptions.py
pagarme_surfmappers/recipient.py
pagarme_surfmappers/transaction.py
pagarme_surfmappers/transfer.py
pagarme_surfmappers/utils.py
pagarme_surfmappers-1.4.1.dist-info/LICENSE
pagarme_surfmappers-1.4.1.dist-info/METADATA
pagarme_surfmappers-1.4.1.dist-info/WHEEL
pagarme_surfmappers-1.4.1.dist-info/top_level.txt
pagarme_surfmappers-1.4.1.dist-info/RECORD
