Metadata-Version: 2.1
Name: pagarme-surfmappers
Version: 1.4.1
Summary: Simple Pagar.me module made by Surfmappers.com
Home-page: https://github.com/YuriAlessandro/pagarme-surfmappers
Author: Yuri Alessandro Martins
Author-email: yuri@surfmappers.com
License: MIT
Platform: UNKNOWN
Classifier: Development Status :: 4 - Beta
Classifier: Intended Audience :: Developers
Classifier: License :: OSI Approved :: MIT License
Classifier: Programming Language :: Python :: 2.7
Classifier: Programming Language :: Python :: 3.6
Requires-Dist: certifi (==2018.10.15)
Requires-Dist: chardet (==3.0.4)
Requires-Dist: idna (==2.7)
Requires-Dist: requests (==2.20.1)
Requires-Dist: urllib3 (==1.24.1)
